LICENSE.txt
README.md
setup.py
pbar_pool/__init__.py
pbar_pool/pbar_pool.py
pbar_pool.egg-info/PKG-INFO
pbar_pool.egg-info/SOURCES.txt
pbar_pool.egg-info/dependency_links.txt
pbar_pool.egg-info/top_level.txt