Metadata-Version: 2.1
Name: pbar-pool
Version: 0.0.2
Summary: A straightforward, dependency free way to update multiple progress bars with python's multiprocessing library.
Home-page: https://github.com/sdtblck/pbar-pool
Author: Sid Black
Author-email: sdtblck@gmail.com
License: MIT
Platform: UNKNOWN
Classifier: License :: OSI Approved :: MIT License
Classifier: Programming Language :: Python :: 3.6
Classifier: Programming Language :: Python :: 3.7
Classifier: Programming Language :: Python :: 3.8
Classifier: Programming Language :: Python :: 3.9
Classifier: Programming Language :: Python :: 3.10
License-File: LICENSE.txt
